[["Map",1,2,9,10,33,34,57,58],"meta::meta",["Map",3,4,5,6,7,8],"astro-version","5.5.4","content-config-digest","65475a3719a60ab6","astro-config-digest","{\"root\":{},\"srcDir\":{},\"publicDir\":{},\"outDir\":{},\"cacheDir\":{},\"site\":\"https://lexingtonthemes.com\",\"compressHTML\":true,\"base\":\"/\",\"trailingSlash\":\"ignore\",\"output\":\"static\",\"scopedStyleStrategy\":\"attribute\",\"build\":{\"format\":\"directory\",\"client\":{},\"server\":{},\"assets\":\"_astro\",\"serverEntry\":\"entry.mjs\",\"redirects\":true,\"inlineStylesheets\":\"auto\",\"concurrency\":1},\"server\":{\"open\":false,\"host\":false,\"port\":4321,\"streaming\":true,\"allowedHosts\":[]},\"redirects\":{},\"image\":{\"endpoint\":{\"route\":\"/_image\"},\"service\":{\"entrypoint\":\"astro/assets/services/sharp\",\"config\":{}},\"domains\":[],\"remotePatterns\":[]},\"devToolbar\":{\"enabled\":true},\"markdown\":{\"syntaxHighlight\":{\"type\":\"shiki\",\"excludeLangs\":[\"math\"]},\"shikiConfig\":{\"langs\":[],\"langAlias\":{},\"theme\":\"github-dark\",\"themes\":{},\"wrap\":false,\"transformers\":[]},\"remarkPlugins\":[],\"rehypePlugins\":[],\"remarkRehype\":{},\"gfm\":true,\"smartypants\":true},\"security\":{\"checkOrigin\":true},\"env\":{\"schema\":{},\"validateSecrets\":false},\"experimental\":{\"clientPrerender\":false,\"contentIntellisense\":false,\"responsiveImages\":false,\"serializeConfig\":false,\"headingIdCompat\":false,\"preserveScriptOrder\":false},\"legacy\":{\"collections\":false}}","woodworking",["Map",11,12,25,26],"circular-saw",{"id":11,"data":13,"filePath":23,"digest":24},{"name":14,"description":15,"price":16,"image":19,"manufacturer":20,"model":21,"batteryType":22},"Circular Saw","Corded circular saw for making precise cuts in wood and other materials.",{"daily":17,"weekly":18},25,125,"https://placehold.co/400x300/EEE/31343C?text=Circular+Saw&font=Montserrat","Makita","XSR01Z","Lithium-Ion","products/woodworking/circular-saw.json","ce4daf4da9f06fda","jigsaw",{"id":25,"data":27,"filePath":31,"digest":32},{"name":28,"description":15,"price":29,"image":30,"manufacturer":20,"model":21,"batteryType":22},"Jigsaw",{"daily":17,"weekly":18},"https://placehold.co/400x300/EEE/31343C?text=Jigsaw&font=Montserrat","products/woodworking/jigsaw.json","8090b0ffc571f6b4","gardening",["Map",35,36,44,45],"lawnmower",{"id":35,"data":37,"filePath":42,"digest":43},{"name":38,"description":15,"price":39,"image":40,"manufacturer":20,"model":21,"batteryType":22,"manual":41},"Lawnmower",{"daily":17,"weekly":18},"https://placehold.co/400x300/EEE/31343C?text=Lawnmower&font=Montserrat","https://www.modesdemploi.fr/stanley/sxvc25ptde/mode-d-emploi","products/gardening/lawnmower.json","34ae670af4467067","leaf-blower",{"id":44,"data":46,"filePath":55,"digest":56},{"name":47,"description":48,"price":49,"image":52,"manufacturer":53,"model":54,"batteryType":22},"Leaf Blower","Electric leaf blower for quick and easy cleanup of leaves and debris.",{"daily":50,"weekly":51},20,100,"https://placehold.co/400x300/EEE/31343C?text=Leaf+Blower&font=Montserrat","Ego","LB5804","products/gardening/leaf-blower.json","5aff611ed334066d","metalworking",["Map",59,60],"plasma-cutter",{"id":59,"data":61,"filePath":65,"digest":66},{"name":62,"description":15,"price":63,"image":64,"manufacturer":20,"model":21,"batteryType":22},"Plasma Cutter",{"daily":17,"weekly":18},"https://placehold.co/400x300/EEE/31343C?text=Plasma+Cutter&font=Montserrat","products/metalworking/plasma-cutter.json","5002e183d08b309f"]